{"cameraMode":{"drawMode":0,"name":"Shaded","section":"Shading Mode"},"sceneLighting":false,"audioPlay":false,"sceneViewState":{"showFog":true,"showMaterialUpdate":false,"showSkybox":false,"showFlares":true,"showImageEffects":true,"showParticleSystems":true,"showVisualEffectGraphs":true,"m_FxEnabled":true},"in2DMode":false,"pivot":{"x":66.80000305175781,"y":10.0,"z":-73.0},"rotation":{"x":-0.4088682532310486,"y":0.44215282797813418,"z":-0.2371489703655243,"w":-0.7623040676116943},"size":4.330127239227295,"orthographic":false}